slack_time/__init__.py
slack_time/api.py
slack_time/utils.py
slack_time-0.1.4.dist-info/LICENSE
slack_time-0.1.4.dist-info/METADATA
slack_time-0.1.4.dist-info/WHEEL
slack_time-0.1.4.dist-info/top_level.txt
slack_time-0.1.4.dist-info/RECORD
