Metadata-Version: 2.1
Name: slack-time
Version: 0.1.4
Summary: A simple, intuitive and fast Slack API client for the Slack Web API
Home-page: http://github.com/jackwardell/SlackTime/
Author: Jack Wardell
Author-email: jack@wardell.xyz
License: UNKNOWN
Keywords: slack api slack-web chat client post get message chatbots bots chatops
Platform: UNKNOWN
Classifier: Programming Language :: Python
Classifier: Programming Language :: Python :: 3
Classifier: Programming Language :: Python :: 3.6
Classifier: Programming Language :: Python :: 3.7
Classifier: Programming Language :: Python :: 3.8
Classifier: License :: OSI Approved :: MIT License
Classifier: Operating System :: OS Independent
Classifier: Natural Language :: English
Classifier: Topic :: Office/Business
Classifier: Topic :: System :: Networking
Classifier: Topic :: Communications :: Chat
Classifier: Intended Audience :: Developers
Requires-Python: >=3.5
Requires-Dist: requests (>=2.2)
